LICENSE
MANIFEST.in
README.rst
requirements.txt
setup.py
test-requirements.txt
avtoolkit/__init__.py
avtoolkit/image.py
avtoolkit/util.py
avtoolkit/video.py
avtoolkit.egg-info/PKG-INFO
avtoolkit.egg-info/SOURCES.txt
avtoolkit.egg-info/dependency_links.txt
avtoolkit.egg-info/namespace_packages.txt
avtoolkit.egg-info/not-zip-safe
avtoolkit.egg-info/top_level.txt