Metadata-Version: 1.1
Name: avtoolkit
Version: 0.0.1
Summary: .. image:: https://travis-ci.org/flyte/avtoolkit.svg?branch=develop
